colorify/__init__.py
colorify/__main__.py
colorify/colorify.py
colorify-1.1.0.dist-info/LICENCE.md
colorify-1.1.0.dist-info/METADATA
colorify-1.1.0.dist-info/WHEEL
colorify-1.1.0.dist-info/entry_points.txt
colorify-1.1.0.dist-info/top_level.txt
colorify-1.1.0.dist-info/RECORD
