Metadata-Version: 2.1
Name: colorify
Version: 1.1.0
Summary: Bring life into your project by adding wonderful colors
Home-page: https://github.com/mahfuznow/colorify
Author: Md. Mahfuzur Rahman
Author-email: contact@mahfuznow.com
License: UNKNOWN
Platform: UNKNOWN
Classifier: Programming Language :: Python :: 3
Classifier: License :: OSI Approved :: MIT License
Classifier: Operating System :: OS Independent
Requires-Python: >=3.6
